odoo/addons/base_territory/README.rst
odoo/addons/base_territory/__init__.py
odoo/addons/base_territory/__manifest__.py
odoo/addons/base_territory/demo/base_territory_demo.xml
odoo/addons/base_territory/i18n/base_territory.pot
odoo/addons/base_territory/i18n/es.po
odoo/addons/base_territory/i18n/es_AR.po
odoo/addons/base_territory/i18n/it.po
odoo/addons/base_territory/i18n/pt_BR.po
odoo/addons/base_territory/i18n/tr.po
odoo/addons/base_territory/models/__init__.py
odoo/addons/base_territory/models/res_branch.py
odoo/addons/base_territory/models/res_country.py
odoo/addons/base_territory/models/res_district.py
odoo/addons/base_territory/models/res_region.py
odoo/addons/base_territory/models/res_territory.py
odoo/addons/base_territory/readme/CONTRIBUTORS.rst
odoo/addons/base_territory/readme/CREDITS.rst
odoo/addons/base_territory/readme/DESCRIPTION.rst
odoo/addons/base_territory/readme/USAGE.rst
odoo/addons/base_territory/security/ir.model.access.csv
odoo/addons/base_territory/static/description/icon.png
odoo/addons/base_territory/static/description/index.html
odoo/addons/base_territory/views/menu.xml
odoo/addons/base_territory/views/res_branch.xml
odoo/addons/base_territory/views/res_country.xml
odoo/addons/base_territory/views/res_district.xml
odoo/addons/base_territory/views/res_region.xml
odoo/addons/base_territory/views/res_territory.xml
odoo14_addon_base_territory-14.0.1.0.1.dist-info/METADATA
odoo14_addon_base_territory-14.0.1.0.1.dist-info/WHEEL
odoo14_addon_base_territory-14.0.1.0.1.dist-info/top_level.txt
odoo14_addon_base_territory-14.0.1.0.1.dist-info/RECORD
